LICENSE
MANIFEST.in
README.md
setup.py
django_model_urls.egg-info/PKG-INFO
django_model_urls.egg-info/SOURCES.txt
django_model_urls.egg-info/dependency_links.txt
django_model_urls.egg-info/not-zip-safe
django_model_urls.egg-info/top_level.txt
model_urls/__init__.py
model_urls/helpers.py
model_urls/urlresolvers.py
model_urls/tests/__init__.py
model_urls/tests/jingo.py
model_urls/tests/models.py
model_urls/tests/urls.py