Metadata-Version: 1.1
Name: django-model-urls
Version: 0.4.0
Summary: DRY way to manage url parameters associated with a model instance based on Jingo.
Home-page: http://github.com/vinyll/django-model-urls
Author: Vincent Agnano
Author-email: vincent.agnano@scopyleft.fr
License: MIT
Platform: UNKNOWN
Classifier: Environment :: Web Environment
Classifier: Intended Audience :: Developers
Classifier: License :: OSI Approved :: MIT License
Classifier: Operating System :: OS Independent
Classifier: Programming Language :: Python
Classifier: Programming Language :: Python :: 2.7
Classifier: Programming Language :: Python :: 3.4
Classifier: Topic :: Utilities
